{
  "SPDXID": "SPDXRef-DOCUMENT",
  "spdxVersion": "SPDX-2.3",
  "name": "SBOM-SPDX-raylib-5.5",
  "creationInfo": {
    "created": "2024-12-30T11:45:12Z",
    "creators": [
      "Tool: https://github.com/Homebrew/brew@4.4.13"
    ]
  },
  "dataLicense": "CC0-1.0",
  "documentNamespace": "https://formulae.brew.sh/spdx/raylib-5.5.json",
  "documentDescribes": [
    "SPDXRef-Archive-raylib-src",
    "SPDXRef-Compiler",
    "SPDXRef-Bottle-raylib"
  ],
  "files": [

  ],
  "packages": [
    {
      "SPDXID": "SPDXRef-Archive-raylib-src",
      "name": "raylib",
      "versionInfo": "5.5",
      "filesAnalyzed": false,
      "licenseDeclared": "NOASSERTION",
      "builtDate": "2024-11-18 12:21:10 UTC",
      "licenseConcluded": "Zlib",
      "downloadLocation": "https://github.com/raysan5/raylib/archive/refs/tags/5.5.tar.gz",
      "copyrightText": "NOASSERTION",
      "externalRefs": [

      ],
      "checksums": [
        {
          "algorithm": "SHA256",
          "checksumValue": "aea98ecf5bc5c5e0b789a76de0083a21a70457050ea4cc2aec7566935f5e258e"
        }
      ]
    },
    {
      "SPDXID": "SPDXRef-Compiler",
      "name": "clang",
      "versionInfo": "16.1",
      "filesAnalyzed": false,
      "licenseDeclared": "NOASSERTION",
      "licenseConcluded": "NOASSERTION",
      "copyrightText": "NOASSERTION",
      "downloadLocation": "NOASSERTION",
      "checksums": [

      ],
      "externalRefs": [

      ]
    },
    {
      "SPDXID": "SPDXRef-Bottle-raylib",
      "name": "raylib",
      "versionInfo": "5.5",
      "filesAnalyzed": false,
      "licenseDeclared": "NOASSERTION",
      "builtDate": "2024-11-18 12:21:10 UTC",
      "licenseConcluded": "Zlib",
      "downloadLocation": "https://ghcr.io/v2/homebrew/core/raylib/blobs/sha256:b2040d26e8f4ff8b35da7e9a6f68186fab5497979d67475314900de05b90f031",
      "copyrightText": "NOASSERTION",
      "externalRefs": [
        {
          "referenceCategory": "PACKAGE-MANAGER",
          "referenceLocator": "pkg:brew/homebrew/core/raylib@5.5",
          "referenceType": "purl"
        }
      ],
      "checksums": [
        {
          "algorithm": "SHA256",
          "checksumValue": "b2040d26e8f4ff8b35da7e9a6f68186fab5497979d67475314900de05b90f031"
        }
      ]
    }
  ],
  "relationships": [
    {
      "spdxElementId": "SPDXRef-File-raylib",
      "relationshipType": "PACKAGE_OF",
      "relatedSpdxElement": "SPDXRef-Archive-raylib-src"
    },
    {
      "spdxElementId": "SPDXRef-Compiler",
      "relationshipType": "BUILD_TOOL_OF",
      "relatedSpdxElement": "SPDXRef-Package-raylib-src"
    }
  ]
}